chef/__init__.py
chef/acl.py
chef/api.py
chef/auth.py
chef/base.py
chef/client.py
chef/data_bag.py
chef/environment.py
chef/exceptions.py
chef/fabric.py
chef/node.py
chef/permissions.py
chef/role.py
chef/rsa.py
chef/search.py
chef/tests/__init__.py
chef/tests/test_api.py
chef/tests/test_client.py
chef/tests/test_data_bag.py
chef/tests/test_environment.py
chef/tests/test_fabric.py
chef/tests/test_node.py
chef/tests/test_role.py
chef/tests/test_rsa.py
chef/tests/test_search.py
chef/utils/__init__.py
chef/utils/file.py
chef/utils/json.py
PyChefRevival-0.3.1.dist-info/LICENSE
PyChefRevival-0.3.1.dist-info/METADATA
PyChefRevival-0.3.1.dist-info/WHEEL
PyChefRevival-0.3.1.dist-info/top_level.txt
PyChefRevival-0.3.1.dist-info/RECORD
